stegart/__init__.py
stegart/stegart.py
stegart-0.1.1.dist-info/DESCRIPTION.rst
stegart-0.1.1.dist-info/METADATA
stegart-0.1.1.dist-info/RECORD
stegart-0.1.1.dist-info/WHEEL
stegart-0.1.1.dist-info/entry_points.txt
stegart-0.1.1.dist-info/metadata.json
stegart-0.1.1.dist-info/top_level.txt
